<?xml version="1.0"?>
<listBibl>
  <bibl id="Agnew_Demas_2002">
    <author n="1">Agnew, N.</author>
    <author n="2">Demas, M.</author>
    <title level="m" lang="eng">Principles for the conservation of heritage sites in China : English-language translation, with Chinese text, of the document issued by China ICOMOS</title>
    <imprint>
      <pubPlace>Los Angeles</pubPlace>
      <publisher>Getty Conservation Institute</publisher>
      <date>2002</date>
    </imprint>
    <keywords>Conservation</keywords>
    <keywords>Heritage</keywords>
    <keywords>China</keywords>
    <genBibl>Conservation</genBibl>
  </bibl>
</listBibl>
