<?xml version="1.0"?>
<bibl id="Ernazarova_1974">
  <author>Ernazarova, T. S</author>
  <title level="a" lang="eng">Dene&#x17E;noe obra&#x161;&#x10D;enie Samrkanda po arxeologo-numis-mati&#x10D;eskim dannym (do na&#x10D;ala IX v.) (The monetary circulation of Samrkand according to archaeological and numismatic data [before the beginning of the 9th century])</title>
  <imprint>
    <title level="j" lang="eng">Afrasiab</title>
    <biblScope type="issue">III</biblScope>
    <biblScope type="pp">155-243</biblScope>
    <date>1974</date>
  </imprint>
  <note/>
  <keywords/>
  <keywords/>
</bibl>
