<?xml version="1.0" encoding="UTF-8"?>
<bibl id="Šiškina_1987">
  <author>Šiškina, G.V.</author>
  <title level="a" lang="rus">Drevnij Samarkand i ego okruga (Ancient Samarkand and its environs)</title>
  <imprint>
    <title level="m" lang="rus">Gorodskaja Kul'tura Baktrii-Toxarestana i Sogda. Antičnost', rannee srednevekov'e. Materialy sovecko-francuskogo kollokviuma (Samarkand 1986)</title>
    <biblScope type="pp">164-170</biblScope>
    <pubPlace>Tashkent</pubPlace>
    <publisher>FAN</publisher>
    <date>1987</date>
  </imprint>
  <note/>
  <keywords>Samarkand</keywords>
  <keywords>History</keywords>
  <genBibl/>
</bibl>
