<?xml version="1.0" encoding="UTF-8"?>
<listBibl>
  <bibl id="Waldschmidt_1972">
    <author>Waldschmidt, Ernst</author>
    <title level="a" lang="eng">A Contribution to our knowledge of SthaviraŚroṇa Koṭiviṃśa</title>
    <imprint>
      <title level="m" lang="eng">S.K.DE Memorial Volume</title>
      <biblScope type="pp">107-116</biblScope>
    </imprint>
    <keywords>manuscripts</keywords>
    <keywords>sanskrit</keywords>
    <keywords>SHT</keywords>
    <keywords>turfan</keywords>
    <keywords>buddhism</keywords>
  </bibl>
</listBibl>
