<?xml version="1.0" encoding="UTF-8"?>
<listBibl>
  <bibl id="Waldschmidt_1967">
    <author>Waldschmidt, Ernst</author>
    <title level="m" lang="ger">Von Ceylon bis Turfan, Schriften zur Geschichte, Literatur, Religion und Kunst des indischen Kulturraumes (Festgabe zum 70. Geburtstag)</title>
    <imprint>
      <pubPlace>Göttingen</pubPlace>
      <date>1967</date>
    </imprint>
    <note/>
    <keywords>manuscript</keywords>
    <keywords>sanskrit</keywords>
    <keywords>turfan</keywords>
    <keywords>SHT</keywords>
    <keywords>buddhism</keywords>
  </bibl>
</listBibl>
